py_tes_estebanfs/__init__.py
py_tes_estebanfs/skeleton.py
py_tes_estebanfs-0.1.dist-info/METADATA
py_tes_estebanfs-0.1.dist-info/RECORD
py_tes_estebanfs-0.1.dist-info/WHEEL
py_tes_estebanfs-0.1.dist-info/top_level.txt
