Metadata-Version: 2.1
Name: py-tes-estebanfs
Version: 0.1
Summary: A random test lib
Home-page: https://github.com/EstebanFS/PypiTest
Author: Esteban Foronda
Author-email: seforonda@gmail.com
License: mit
Keywords: testing,logging,example
Platform: any
Classifier: Development Status :: 4 - Beta
Classifier: Programming Language :: Python
